[
  {
    "tractorId": 101,
    "unitNumber": "T-101",
    "make": "Freightliner",
    "model": "Cascadia",
    "year": 2021,
    "status": "Available",
    "location": "Dallas, TX",
    "driverId": 1,
    "isActive": true
  },
  {
    "tractorId": 102,
    "unitNumber": "T-102",
    "make": "Volvo",
    "model": "VNL 760",
    "year": 2020,
    "status": "On Load",
    "location": "Memphis, TN",
    "driverId": 2,
    "isActive": true
  },
  {
    "tractorId": 103,
    "unitNumber": "T-103",
    "make": "Kenworth",
    "model": "T680",
    "year": 2019,
    "status": "Off Duty",
    "location": "Nashville, TN",
    "driverId": 3,
    "isActive": true
  },
  {
    "tractorId": 104,
    "unitNumber": "T-104",
    "make": "Peterbilt",
    "model": "579",
    "year": 2022,
    "status": "In Transit",
    "location": "Atlanta, GA",
    "driverId": 4,
    "isActive": true
  },
  {
    "tractorId": 105,
    "unitNumber": "T-105",
    "make": "International",
    "model": "LT Series",
    "year": 2021,
    "status": "Available",
    "location": "Chicago, IL",
    "driverId": 5,
    "isActive": true
  }
]
